moleskin/__init__.py
moleskin/moleskin.py
moleskin/test_moleskin.py
moleskin-1.5.1.dist-info/METADATA
moleskin-1.5.1.dist-info/RECORD
moleskin-1.5.1.dist-info/WHEEL
moleskin-1.5.1.dist-info/top_level.txt
