Metadata-Version: 2.1
Name: moleskin
Version: 1.5.1
Summary: A print and debugging utility that makes your error printouts look nice
Home-page: https://github.com/episodeyang/moleskin
Author: Ge Yang
Author-email: yangge1987@gmail.com
License: UNKNOWN
Keywords: moleskin,logging,debug,debugging,timer,timeit,decorator,stopwatch,tic,toc
Platform: UNKNOWN
Classifier: Development Status :: 4 - Beta
Classifier: Intended Audience :: Science/Research
Classifier: Programming Language :: Python :: 3
Requires-Dist: termcolor
Requires-Dist: pprint
Requires-Dist: boltons
